{"aggregationId": "investor_supplier_network", "title": "Where the money go? From Investors to Suppliers! (2021)", "company": 1829050, "companyName": "Asos", "year": 2021, "comment": null, "network": {"nodes": [{"_id": 1829050, "label": "Asos", "color": "rgba(72, 76, 157, 1)"}, {"_id": 4050033, "label": "TIAA-CREF Investment Management LLC", "color": "rgba(29, 30, 63, 1)"}, {"_id": 4050695, "label": "T. Rowe Price Associates Inc.", "color": "rgba(29, 30, 63, 1)"}, {"_id": 5652621, "label": "American Century Investment Management, Inc.", "color": "rgba(29, 30, 63, 1)"}, {"_id": 7890158, "label": "BlackRock Fund Advisors", "color": "rgba(29, 30, 63, 1)"}], "edges": [{"_id": 0, "from": 4050033, "to": 1829050, "label": "is Shareholder of\n (1.65%)"}, {"_id": 1, "from": 4050695, "to": 1829050, "label": "is Shareholder of\n (5.49%)"}, {"_id": 2, "from": 5652621, "to": 1829050, "label": "is Shareholder of\n (2.13%)"}, {"_id": 3, "from": 7890158, "to": 1829050, "label": "is Shareholder of\n (1.1%)"}]}, "_class": "org.wikirate.apparel.project.aggregation.Aggregation"}