{"aggregationId": "investor_supplier_network", "title": "Where the money go? From Investors to Suppliers! (2021)", "company": 3624454, "companyName": "Grendene", "year": 2021, "comment": null, "network": {"nodes": [{"id": 3624454, "label": "Grendene", "color": "rgba(247, 115, 61, 1)", "size": 10}, {"id": 2637940, "label": "BTG Pactual", "size": 2.11, "color": "rgba(29, 30, 63, 1)"}, {"id": 3755952, "label": "The Vanguard Group", "size": 0.87, "color": "rgba(29, 30, 63, 1)"}, {"id": 5651517, "label": "eQ Varainhoito Oy", "size": 0.44, "color": "rgba(29, 30, 63, 1)"}, {"id": 5653142, "label": "Templeton Asset Management Ltd.", "size": 0.36, "color": "rgba(29, 30, 63, 1)"}, {"id": 7622003, "label": "Jupiter Asset Management", "size": 0.64, "color": "rgba(29, 30, 63, 1)"}, {"id": 7890154, "label": "BB Gestao de Recursos DTVM SA", "size": 0.37, "color": "rgba(29, 30, 63, 1)"}, {"id": 7890158, "label": "BlackRock Fund Advisors", "size": 0.48, "color": "rgba(29, 30, 63, 1)"}, {"id": 7890159, "label": "BNY Mellon Administracao de Ativos Ltda.", "size": 0.5, "color": "rgba(29, 30, 63, 1)"}, {"id": 7890160, "label": "Bogari Gestao de Investimentos Ltda.", "size": 1.98, "color": "rgba(29, 30, 63, 1)"}], "edges": [{"id": 0, "from": 2637940, "to": 3624454, "label": "is Shareholder of\n (2.11%)"}, {"id": 1, "from": 3755952, "to": 3624454, "label": "is Shareholder of\n (0.87%)"}, {"id": 2, "from": 5651517, "to": 3624454, "label": "is Shareholder of\n (0.44%)"}, {"id": 3, "from": 5653142, "to": 3624454, "label": "is Shareholder of\n (0.36%)"}, {"id": 4, "from": 7622003, "to": 3624454, "label": "is Shareholder of\n (0.64%)"}, {"id": 5, "from": 7890154, "to": 3624454, "label": "is Shareholder of\n (0.37%)"}, {"id": 6, "from": 7890158, "to": 3624454, "label": "is Shareholder of\n (0.48%)"}, {"id": 7, "from": 7890159, "to": 3624454, "label": "is Shareholder of\n (0.5%)"}, {"id": 8, "from": 7890160, "to": 3624454, "label": "is Shareholder of\n (1.98%)"}]}, "_class": "org.wikirate.apparel.project.aggregation.Aggregation"}